smsframework_gatewayapi/__init__.py
smsframework_gatewayapi/error.py
smsframework_gatewayapi/provider.py
smsframework_gatewayapi/receiver.py
smsframework_gatewayapi/status.py
smsframework_gatewayapi-0.0.1.dist-info/LICENSE
smsframework_gatewayapi-0.0.1.dist-info/METADATA
smsframework_gatewayapi-0.0.1.dist-info/WHEEL
smsframework_gatewayapi-0.0.1.dist-info/top_level.txt
smsframework_gatewayapi-0.0.1.dist-info/RECORD
