Metadata-Version: 2.1
Name: smsframework-gatewayapi
Version: 0.0.1
Summary: SMS framework: GatewayApi provider 
Home-page: https://github.com/kolypto/py-smsframework-gatewayapi
Author: Mark Vartanyan
Author-email: kolypto@gmail.com
License: BSD
Keywords: sms,message,notification,receive,send,gatewayapi
Platform: any
Classifier: Development Status :: 5 - Production/Stable
Classifier: Intended Audience :: Developers
Classifier: Natural Language :: English
Classifier: Programming Language :: Python :: 2
Classifier: Programming Language :: Python :: 3
Classifier: Operating System :: OS Independent
Requires-Dist: smsframework (>=0.0.9)
Requires-Dist: requests-oauthlib (>=1.2.0)
Provides-Extra: receiver
Requires-Dist: flask (>=0.10) ; extra == 'receiver'
Requires-Dist: pyjwt (>=1.7.1) ; extra == 'receiver'
